one_updater/__init__.py
one_updater/cli.py
one_updater/package_managers/__init__.py
one_updater/package_managers/apt.py
one_updater/package_managers/base.py
one_updater/package_managers/basher.py
one_updater/package_managers/brew.py
one_updater/package_managers/cargo.py
one_updater/package_managers/dnf.py
one_updater/package_managers/flatpak.py
one_updater/package_managers/gem.py
one_updater/package_managers/ghcli.py
one_updater/package_managers/go.py
one_updater/package_managers/krew.py
one_updater/package_managers/micro.py
one_updater/package_managers/npm.py
one_updater/package_managers/pacman.py
one_updater/package_managers/pip.py
one_updater/package_managers/pipx.py
one_updater/package_managers/pkgx.py
one_updater/package_managers/registry.py
one_updater/package_managers/snap.py
one_updater/package_managers/tldr.py
one_updater/package_managers/uv.py
one_updater/package_managers/vagrant.py
one_updater-1.0.0.dist-info/licenses/LICENSE.md
one_updater-1.0.0.dist-info/METADATA
one_updater-1.0.0.dist-info/WHEEL
one_updater-1.0.0.dist-info/entry_points.txt
one_updater-1.0.0.dist-info/top_level.txt
one_updater-1.0.0.dist-info/RECORD
