Metadata-Version: 2.4
Name: one-updater
Version: 1.0.0
Summary: One tool many packages
Author-email: Tim Bryant <timothybryant3@gmail.com>
Requires-Python: <3.14,>=3.11
License-File: LICENSE.md
Requires-Dist: pyyaml
Requires-Dist: rich
Requires-Dist: python-semantic-release
Provides-Extra: dev
Requires-Dist: autopep8; extra == "dev"
Requires-Dist: black; extra == "dev"
Requires-Dist: pytest; extra == "dev"
Requires-Dist: pre-commit; extra == "dev"
Requires-Dist: isort; extra == "dev"
Requires-Dist: pyinstaller; extra == "dev"
Requires-Dist: pyyaml; extra == "dev"
Dynamic: license-file
